sendpulse_api/__init__.py
sendpulse_api/client.py
sendpulse_api/version.py
sendpulse_api-1.0.0.dist-info/DESCRIPTION.rst
sendpulse_api-1.0.0.dist-info/METADATA
sendpulse_api-1.0.0.dist-info/RECORD
sendpulse_api-1.0.0.dist-info/WHEEL
sendpulse_api-1.0.0.dist-info/metadata.json
sendpulse_api-1.0.0.dist-info/top_level.txt
